django_readedit_switch_admin/__init__.py
django_readedit_switch_admin/admin.py
django_readedit_switch_admin/migrations/__init__.py
django_readedit_switch_admin/static/admin/css/django-readedit-switch-admin.css
django_readedit_switch_admin/static/admin/js/django-readedit-switch-admin.js
django_readedit_switch_admin/templates/admin/change_form.html
django_readedit_switch_admin/templates/admin/django_readedit_switch_admin_submit_row.html
django_readedit_switch_admin/templatetags/__init__.py
django_readedit_switch_admin/templatetags/django_readedit_switch_admin_tags.py
django_readedit_switch_admin-0.4.7.dist-info/LICENSE
django_readedit_switch_admin-0.4.7.dist-info/METADATA
django_readedit_switch_admin-0.4.7.dist-info/WHEEL
django_readedit_switch_admin-0.4.7.dist-info/top_level.txt
django_readedit_switch_admin-0.4.7.dist-info/RECORD
