Metadata-Version: 2.1
Name: django-readedit-switch-admin
Version: 0.4.7
Summary: Read item detail first, and click the Edit switch button to turn to edit view.
Author: Huang ChuanZhe
Author-email: huangchuanzhe@zencore.cn
Maintainer: Huang ChuanZhe
Maintainer-email: huangchuanzhe@zencore.cn
License: MIT
Keywords: django admin extentions,django readedit switch admin
Classifier: Development Status :: 5 - Production/Stable
Classifier: Intended Audience :: Developers
Classifier: Topic :: Software Development :: Libraries :: Python Modules
Classifier: License :: OSI Approved :: MIT License
Classifier: Programming Language :: Python :: 3
Classifier: Programming Language :: Python :: 3 :: Only
License-File: LICENSE
Requires-Dist: Django >=2.2.20
